numbers_c2pa/__init__.py
numbers_c2pa/core.py
numbers_c2pa/exceptions.py
numbers_c2pa/utils.py
numbers_c2pa-0.4.0.dist-info/licenses/LICENSE
numbers_c2pa-0.4.0.dist-info/METADATA
numbers_c2pa-0.4.0.dist-info/WHEEL
numbers_c2pa-0.4.0.dist-info/top_level.txt
numbers_c2pa-0.4.0.dist-info/zip-safe
numbers_c2pa-0.4.0.dist-info/RECORD
