Metadata-Version: 2.4
Name: numbers-c2pa
Version: 0.4.0
Summary: Numbers C2PA tool
Home-page: https://github.com/numbersprotocol/numbers-c2pa
Author: Numbers Co., Inc
Author-email: dev@numbersprotocol.io
Keywords: authenticity
Classifier: Development Status :: 4 - Beta
Classifier: License :: OSI Approved :: MIT License
Classifier: Programming Language :: Python :: 3.9
Classifier: Programming Language :: Python :: 3.10
Classifier: Programming Language :: Python :: 3.11
Classifier: Programming Language :: Python :: 3.12
Classifier: Programming Language :: Python :: 3.13
Requires-Python: >=3.9
License-File: LICENSE
Requires-Dist: cryptography
Requires-Dist: requests
Provides-Extra: tests
Requires-Dist: tox; extra == "tests"
Provides-Extra: docs
Requires-Dist: sphinx; extra == "docs"
Dynamic: license-file
